XStatic_Angular_Material-1.1.5.2-py2.7-nspkg.pth
XStatic_Angular_Material-1.1.5.2.dist-info/METADATA
XStatic_Angular_Material-1.1.5.2.dist-info/RECORD
XStatic_Angular_Material-1.1.5.2.dist-info/WHEEL
XStatic_Angular_Material-1.1.5.2.dist-info/namespace_packages.txt
XStatic_Angular_Material-1.1.5.2.dist-info/top_level.txt
xstatic/pkg/angular_material/__init__.py
xstatic/pkg/angular_material/data/angular-material-mocks.js
xstatic/pkg/angular_material/data/angular-material.css
xstatic/pkg/angular_material/data/angular-material.js
xstatic/pkg/angular_material/data/angular-material.scss
xstatic/pkg/angular_material/data/layouts/angular-material.layout-attributes.css
xstatic/pkg/angular_material/data/layouts/angular-material.layout-attributes.scss
xstatic/pkg/angular_material/data/layouts/angular-material.layouts.css
xstatic/pkg/angular_material/data/layouts/angular-material.layouts.ie_fixes.css
xstatic/pkg/angular_material/data/layouts/angular-material.layouts.scss
xstatic/pkg/angular_material/data/modules/closure/autocomplete/autocomplete-default-theme.css
xstatic/pkg/angular_material/data/modules/closure/autocomplete/autocomplete.css
xstatic/pkg/angular_material/data/modules/closure/autocomplete/autocomplete.js
xstatic/pkg/angular_material/data/modules/closure/backdrop/backdrop-default-theme.css
xstatic/pkg/angular_material/data/modules/closure/backdrop/backdrop.css
xstatic/pkg/angular_material/data/modules/closure/backdrop/backdrop.js
xstatic/pkg/angular_material/data/modules/closure/bottomSheet/bottomSheet-default-theme.css
xstatic/pkg/angular_material/data/modules/closure/bottomSheet/bottomSheet.css
xstatic/pkg/angular_material/data/modules/closure/bottomSheet/bottomSheet.js
xstatic/pkg/angular_material/data/modules/closure/button/button-default-theme.css
xstatic/pkg/angular_material/data/modules/closure/button/button.css
xstatic/pkg/angular_material/data/modules/closure/button/button.js
xstatic/pkg/angular_material/data/modules/closure/card/card-default-theme.css
xstatic/pkg/angular_material/data/modules/closure/card/card.css
xstatic/pkg/angular_material/data/modules/closure/card/card.js
xstatic/pkg/angular_material/data/modules/closure/checkbox/checkbox-default-theme.css
