Metadata-Version: 2.1
Name: XStatic-Angular-Material
Version: 1.1.5.2
Summary: Angular-Material 1.1.5 (XStatic packaging standard)
Home-page: https://github.com/angular/material
Maintainer: xinni.ge
Maintainer-email: xinni.ge@ntt.com
License: MIT
Keywords: angular_material xstatic
Platform: any
